marcdb
