Metadata-Version: 1.0
Name: marcdb
Version: 0.92
Summary: parse MARC data and store into a rdbms
Home-page: http://inkdroid.org/bzr/marcdb
Author: Ed Summers
Author-email: ehs@pobox.com
License: UNKNOWN
Platform: UNKNOWN
